iseroo_kotprog/__init__.py
iseroo_kotprog/main.py
iseroo_kotprog/tasks.txt
iseroo_kotprog/assets/image_locations.json
iseroo_kotprog/assets/images/Inventory_Bar.png
iseroo_kotprog/assets/images/Inventory_Slot.png
iseroo_kotprog/assets/images/Inventory_select.png
iseroo_kotprog/assets/images/cat.png
iseroo_kotprog/assets/images/grass.png
iseroo_kotprog/assets/images/items.png
iseroo_kotprog/assets/images/loading_screen.png
iseroo_kotprog/assets/images/map/level00.png
iseroo_kotprog/config/config.json
iseroo_kotprog/utils/button.py
iseroo_kotprog/utils/character.py
iseroo_kotprog/utils/config.py
iseroo_kotprog/utils/functions.py
iseroo_kotprog/utils/game_map.py
iseroo_kotprog/utils/health_bars.py
iseroo_kotprog/utils/inventory.py
iseroo_kotprog/utils/item.py
iseroo_kotprog/utils/map_reader.py
iseroo_kotprog/utils/message_service.py
iseroo_kotprog/utils/text_display.py
iseroo_kotprog/utils/__pycache__/character.cpython-310.pyc
iseroo_kotprog/utils/__pycache__/config.cpython-310.pyc
iseroo_kotprog/utils/__pycache__/functions.cpython-310.pyc
iseroo_kotprog/utils/__pycache__/game_map.cpython-310.pyc
iseroo_kotprog/utils/__pycache__/health_bars.cpython-310.pyc
iseroo_kotprog/utils/__pycache__/inventory.cpython-310.pyc
iseroo_kotprog/utils/__pycache__/item.cpython-310.pyc
iseroo_kotprog/utils/__pycache__/item.cpython-311.pyc
iseroo_kotprog/utils/__pycache__/map_reader.cpython-310.pyc
iseroo_kotprog/utils/__pycache__/map_reader.cpython-311.pyc
iseroo_kotprog/utils/__pycache__/message_service.cpython-310.pyc
iseroo_kotprog/utils/__pycache__/message_service.cpython-311.pyc
iseroo_kotprog/utils/__pycache__/text_display.cpython-310.pyc
iseroo_kotprog-0.0.1.dist-info/METADATA
iseroo_kotprog-0.0.1.dist-info/WHEEL
iseroo_kotprog-0.0.1.dist-info/entry_points.txt
iseroo_kotprog-0.0.1.dist-info/top_level.txt
iseroo_kotprog-0.0.1.dist-info/RECORD
